paas_devops/__init__.py
paas_devops-0.1.0.dist-info/METADATA
paas_devops-0.1.0.dist-info/WHEEL
paas_devops-0.1.0.dist-info/RECORD
